lektor_debug.py
lektor_debug-0.1.5.dist-info/LICENSE
lektor_debug-0.1.5.dist-info/METADATA
lektor_debug-0.1.5.dist-info/WHEEL
lektor_debug-0.1.5.dist-info/entry_points.txt
lektor_debug-0.1.5.dist-info/top_level.txt
lektor_debug-0.1.5.dist-info/RECORD
