Metadata-Version: 2.1
Name: lektor-debug
Version: 0.1.5
Summary: A Lektor Plugin for Debugging Help
Home-page: https://github.com/terminal-labs/lektor-debug
Author: Joseph Nix
Author-email: nixjdm@terminallabs.com
License: BSD-3-Clause
Keywords: Lektor plugin
Classifier: Framework :: Lektor
Classifier: Environment :: Plugins
License-File: LICENSE
